fgroups/__init__.py
fgroups/_temp.py
fgroups/group_structure.py
fgroups/groups.py
finite_groups-0.0.2.dist-info/LICENSE
finite_groups-0.0.2.dist-info/METADATA
finite_groups-0.0.2.dist-info/WHEEL
finite_groups-0.0.2.dist-info/top_level.txt
finite_groups-0.0.2.dist-info/RECORD
