Metadata-Version: 2.1
Name: finite-groups
Version: 0.0.2
Summary: Finite Groups Computations
Home-page: UNKNOWN
Author: Cris Torres
Author-email: cristobal_javier@hotmail.com
License: MIT License
Project-URL: GitHub, https://github.com/CrisLeaf/finite-groups
Platform: UNKNOWN
Classifier: Development Status :: 1 - Planning
Classifier: Intended Audience :: Science/Research
Classifier: Intended Audience :: Developers
Classifier: License :: OSI Approved :: MIT License
Classifier: Programming Language :: Python :: 3.9
Classifier: Topic :: Scientific/Engineering
Classifier: Operating System :: POSIX
Classifier: Operating System :: Microsoft :: Windows
Classifier: Operating System :: Unix
Classifier: Operating System :: MacOS
License-File: LICENSE
Requires-Dist: numpy
